corelay/__init__.py
corelay/base.py
corelay/plugboard.py
corelay/tracker.py
corelay/utils.py
corelay/io/__init__.py
corelay/io/hashing.py
corelay/io/storage.py
corelay/pipeline/__init__.py
corelay/pipeline/base.py
corelay/pipeline/spectral.py
corelay/processor/__init__.py
corelay/processor/affinity.py
corelay/processor/base.py
corelay/processor/clustering.py
corelay/processor/distance.py
corelay/processor/embedding.py
corelay/processor/flow.py
corelay/processor/laplacian.py
corelay/processor/preprocessing.py
corelay-0.2.1.dist-info/COPYING
corelay-0.2.1.dist-info/COPYING.LESSER
corelay-0.2.1.dist-info/LICENSE
corelay-0.2.1.dist-info/METADATA
corelay-0.2.1.dist-info/WHEEL
corelay-0.2.1.dist-info/top_level.txt
corelay-0.2.1.dist-info/RECORD
