Metadata-Version: 2.1
Name: corelay
Version: 0.2.1
Summary: Quickly compose single-machine analysis pipelines.
Home-page: https://github.com/virelay/corelay
Author: chrstphr
Author-email: corelay@j0d.de
Classifier: Development Status :: 3 - Alpha
Classifier: License :: OSI Approved :: GNU Lesser General Public License v3 or later (LGPLv3+)
Classifier: Programming Language :: Python :: 3.7
Classifier: Programming Language :: Python :: 3.8
Classifier: Programming Language :: Python :: 3.9
Requires-Python: >=3.7
License-File: LICENSE
License-File: COPYING
License-File: COPYING.LESSER
Requires-Dist: h5py (>=2.9.0)
Requires-Dist: matplotlib (>=3.0.3)
Requires-Dist: numpy (>=1.16.3)
Requires-Dist: scikit-learn (>=0.20.3)
Requires-Dist: scipy (>=1.2.1)
Requires-Dist: Click (>=7.0)
Requires-Dist: scikit-image (>=0.18.0)
Requires-Dist: metrohash-python (>=1.1.3.post2)
Provides-Extra: docs
Requires-Dist: sphinx-copybutton (>=0.4.0) ; extra == 'docs'
Requires-Dist: sphinx-rtd-theme (>=1.0.0) ; extra == 'docs'
Requires-Dist: sphinxcontrib.datatemplates (>=0.9.0) ; extra == 'docs'
Requires-Dist: sphinxcontrib.bibtex (>=2.4.1) ; extra == 'docs'
Provides-Extra: hdbscan
Requires-Dist: hdbscan (>=0.8.22) ; extra == 'hdbscan'
Provides-Extra: tests
Requires-Dist: pytest ; extra == 'tests'
Requires-Dist: pytest-cov ; extra == 'tests'
Provides-Extra: umap
Requires-Dist: umap-learn (>=0.3.9) ; extra == 'umap'
